netmagus/__init__.py
netmagus/__main__.py
netmagus/form.py
netmagus/netop.py
netmagus/py.typed
netmagus/rpc.py
netmagus/screen.py
netmagus/session.py
netmagus-1.0.0.dist-info/METADATA
netmagus-1.0.0.dist-info/WHEEL
netmagus-1.0.0.dist-info/licenses/AUTHORS.rst
netmagus-1.0.0.dist-info/licenses/LICENSE
netmagus-1.0.0.dist-info/RECORD
